{
  "title": "Benefícios do pós obra:",
  "text": "Remove os resíduos de obra com eficácia e sem agredir as superfícies;",
  "text2":" Ideal em ambientes com excesso de concreto, cimento, reboco, argamassa, cal, rejuntes, gesso e terra em obras;",
  "text3":"Remove respingos de tintas de base água recentes em pisos não porosos;",
  "text4": " Muito versátil: Ótimo para quem presta serviços (uso profissional). Excelente para residências (uso doméstico);",
  "text5": "Acabamento perfeito para sua obra."
}


